fett/__init__.py
fett/py.typed
fett-0.4.0.dist-info/LICENSE
fett-0.4.0.dist-info/WHEEL
fett-0.4.0.dist-info/METADATA
fett-0.4.0.dist-info/RECORD
