Metadata-Version: 2.1
Name: fett
Version: 0.4.0
Summary: A fast indentation-preserving template engine.
License: MIT
Author: Heli Aldridge
Author-email: heli@heli.pet
Requires-Python: >=3.7,<4.0
Classifier: License :: OSI Approved :: MIT License
Classifier: Programming Language :: Python :: 3
Classifier: Programming Language :: Python :: 3.7
Classifier: Programming Language :: Python :: 3.8
Classifier: Programming Language :: Python :: 3.9
Classifier: Programming Language :: Python :: 3.10
